ttldict2/__init__.py
ttldict2/impl.py
ttldict2-0.1.1.dist-info/LICENSE
ttldict2-0.1.1.dist-info/METADATA
ttldict2-0.1.1.dist-info/NOTICE
ttldict2-0.1.1.dist-info/WHEEL
ttldict2-0.1.1.dist-info/top_level.txt
ttldict2-0.1.1.dist-info/RECORD
