Metadata-Version: 2.1
Name: ttldict2
Version: 0.1.1
Summary: Another dictionary with expiring keys.
Home-page: https://github.com/Traktormaster/ttldict2
Author: Nándor Mátravölgyi
Author-email: nandor.matra@gmail.com
License: Apache 2.0
Platform: UNKNOWN
Classifier: Programming Language :: Python :: 3
Classifier: Programming Language :: Python :: 3.7
Classifier: Programming Language :: Python :: 3.8
Classifier: Programming Language :: Python :: 3.9
Classifier: Programming Language :: Python :: Implementation :: CPython
Classifier: Programming Language :: Python :: Implementation :: PyPy
Classifier: Intended Audience :: Developers
Classifier: License :: OSI Approved :: Apache Software License
